deeplearningai/__init__.py
deeplearningai-0.1.0.dist-info/METADATA
deeplearningai-0.1.0.dist-info/WHEEL
deeplearningai-0.1.0.dist-info/RECORD
