Metadata-Version: 2.1
Name: deeplearningai
Version: 0.1.0
Summary: test
Author: Andrew Ng
Author-email: ng@deeplearning.ai
Requires-Python: >=3.12,<4.0
Classifier: Programming Language :: Python :: 3
Classifier: Programming Language :: Python :: 3.12
Requires-Dist: numpy (>=2.0.1,<3.0.0)
